event_analytics/__init__.py
event_analytics/event_analytics.py
event_analytics/test.py
event_analytics-0.1.1.dist-info/LICENSE
event_analytics-0.1.1.dist-info/METADATA
event_analytics-0.1.1.dist-info/WHEEL
event_analytics-0.1.1.dist-info/top_level.txt
event_analytics-0.1.1.dist-info/RECORD
