Metadata-Version: 2.1
Name: event-analytics
Version: 0.1.1
Summary: An Event Analytics package to help organizers analyze, segment & understand Audience & their behavior. Built with love by Babel!
Home-page: https://github.com/babel-data/event_analytics
Author: Babel Pte. Ltd
Author-email: contact@babel.sg
License: UNKNOWN
Platform: UNKNOWN
Classifier: Programming Language :: Python :: 3
Classifier: License :: OSI Approved :: MIT License
Classifier: Operating System :: OS Independent
Requires-Python: >=3.6
